starlette_x_bugsnag/__init__.py
starlette_x_bugsnag/middleware.py
starlette_x_bugsnag-0.1.6.dist-info/LICENSE
starlette_x_bugsnag-0.1.6.dist-info/WHEEL
starlette_x_bugsnag-0.1.6.dist-info/METADATA
starlette_x_bugsnag-0.1.6.dist-info/RECORD
