Metadata-Version: 2.1
Name: starlette-x-bugsnag
Version: 0.1.6
Summary: Shiny Bugsnag integration for Starlette framework
Home-page: https://github.com/2tunnels/starlette-x-bugsnag
License: MIT
Keywords: starlette,bugsnag,asgi
Author: Vlad Dmitrievich
Author-email: me@2tunnels.com
Requires-Python: >=3.6,<4.0
Classifier: Development Status :: 4 - Beta
Classifier: Environment :: Web Environment
Classifier: License :: OSI Approved :: MIT License
Classifier: Programming Language :: Python :: 3
Classifier: Programming Language :: Python :: 3.6
Classifier: Programming Language :: Python :: 3.7
Classifier: Programming Language :: Python :: 3.8
Classifier: Programming Language :: Python :: Implementation :: CPython
Classifier: Topic :: System :: Logging
Classifier: Topic :: System :: Networking
Classifier: Typing :: Typed
Requires-Dist: bugsnag (>=3.6.0,<4.0.0)
Requires-Dist: importlib-metadata (>=1.6.0,<2.0.0)
Requires-Dist: starlette (>=0.13.0,<0.14.0)
Project-URL: Repository, https://github.com/2tunnels/starlette-x-bugsnag
